{
  "version": "6",
  "dialect": "sqlite",
  "id": "a544d1d9-6e34-40a5-b813-4b5360fbc509",
  "prevId": "f891f90d-67fa-4523-9f92-96bef902f6c2",
  "tables": {
    "category": {
      "name": "category",
      "columns": {
        "id": {
          "name": "id",
          "type": "text",
          "primaryKey": true,
          "notNull": true,
          "autoincrement": false
        },
        "name": {
          "name": "name",
          "type": "text",
          "primaryKey": false,
          "notNull": true,
          "autoincrement": false
        },
        "direction": {
          "name": "direction",
          "type": "text",
          "primaryKey": false,
          "notNull": true,
          "autoincrement": false
        },
        "created_at": {
          "name": "created_at",
          "type": "integer",
          "primaryKey": false,
          "notNull": true,
          "autoincrement": false
        },
        "updated_at": {
          "name": "updated_at",
          "type": "integer",
          "primaryKey": false,
          "notNull": true,
          "autoincrement": false
        }
      },
      "indexes": {
        "uniq_category_name": {
          "name": "uniq_category_name",
          "columns": [
            "name"
          ],
          "isUnique": true
        }
      },
      "foreignKeys": {},
      "compositePrimaryKeys": {},
      "uniqueConstraints": {},
      "checkConstraints": {}
    },
    "category_scoreable": {
      "name": "category_scoreable",
      "columns": {
        "category_id": {
          "name": "category_id",
          "type": "text",
          "primaryKey": false,
          "notNull": true,
          "autoincrement": false
        },
        "scoreable_id": {
          "name": "scoreable_id",
          "type": "text",
          "primaryKey": false,
          "notNull": true,
          "autoincrement": false
        }
      },
      "indexes": {
        "category_scoreable_scoreable": {
          "name": "category_scoreable_scoreable",
          "columns": [
            "scoreable_id"
          ],
          "isUnique": false
        }
      },
      "foreignKeys": {
        "category_scoreable_category_id_category_id_fk": {
          "name": "category_scoreable_category_id_category_id_fk",
          "tableFrom": "category_scoreable",
          "tableTo": "category",
          "columnsFrom": [
            "category_id"
          ],
          "columnsTo": [
            "id"
          ],
          "onDelete": "cascade",
          "onUpdate": "cascade"
        },
        "category_scoreable_scoreable_id_scoreable_id_fk": {
          "name": "category_scoreable_scoreable_id_scoreable_id_fk",
          "tableFrom": "category_scoreable",
          "tableTo": "scoreable",
          "columnsFrom": [
            "scoreable_id"
          ],
          "columnsTo": [
            "id"
          ],
          "onDelete": "cascade",
          "onUpdate": "cascade"
        }
      },
      "compositePrimaryKeys": {
        "category_scoreable_pk": {
          "columns": [
            "category_id",
            "scoreable_id"
          ],
          "name": "category_scoreable_pk"
        }
      },
      "uniqueConstraints": {},
      "checkConstraints": {}
    },
    "division": {
      "name": "division",
      "columns": {
        "id": {
          "name": "id",
          "type": "text",
          "primaryKey": true,
          "notNull": true,
          "autoincrement": false
        },
        "name": {
          "name": "name",
          "type": "text",
          "primaryKey": false,
          "notNull": true,
          "autoincrement": false
        },
        "created_at": {
          "name": "created_at",
          "type": "integer",
          "primaryKey": false,
          "notNull": true,
          "autoincrement": false
        },
        "updated_at": {
          "name": "updated_at",
          "type": "integer",
          "primaryKey": false,
          "notNull": true,
          "autoincrement": false
        }
      },
      "indexes": {
        "uniq_division_name": {
          "name": "uniq_division_name",
          "columns": [
            "name"
          ],
          "isUnique": true
        }
      },
      "foreignKeys": {},
      "compositePrimaryKeys": {},
      "uniqueConstraints": {},
      "checkConstraints": {}
    },
    "division_category": {
      "name": "division_category",
      "columns": {
        "division_id": {
          "name": "division_id",
          "type": "text",
          "primaryKey": false,
          "notNull": true,
          "autoincrement": false
        },
        "category_id": {
          "name": "category_id",
          "type": "text",
          "primaryKey": false,
          "notNull": true,
          "autoincrement": false
        },
        "depth": {
          "name": "depth",
          "type": "integer",
          "primaryKey": false,
          "notNull": true,
          "autoincrement": false,
          "default": 1
        }
      },
      "indexes": {
        "division_category_category": {
          "name": "division_category_category",
          "columns": [
            "category_id"
          ],
          "isUnique": false
        }
      },
      "foreignKeys": {
        "division_category_division_id_division_id_fk": {
          "name": "division_category_division_id_division_id_fk",
          "tableFrom": "division_category",
          "tableTo": "division",
          "columnsFrom": [
            "division_id"
          ],
          "columnsTo": [
            "id"
          ],
          "onDelete": "cascade",
          "onUpdate": "cascade"
        },
        "division_category_category_id_category_id_fk": {
          "name": "division_category_category_id_category_id_fk",
          "tableFrom": "division_category",
          "tableTo": "category",
          "columnsFrom": [
            "category_id"
          ],
          "columnsTo": [
            "id"
          ],
          "onDelete": "cascade",
          "onUpdate": "cascade"
        }
      },
      "compositePrimaryKeys": {
        "division_category_pk": {
          "columns": [
            "division_id",
            "category_id"
          ],
          "name": "division_category_pk"
        }
      },
      "uniqueConstraints": {},
      "checkConstraints": {}
    },
    "event": {
      "name": "event",
      "columns": {
        "id": {
          "name": "id",
          "type": "text",
          "primaryKey": true,
          "notNull": true,
          "autoincrement": false
        },
        "type": {
          "name": "type",
          "type": "text",
          "primaryKey": false,
          "notNull": true,
          "autoincrement": false
        },
        "ts": {
          "name": "ts",
          "type": "integer",
          "primaryKey": false,
          "notNull": true,
          "autoincrement": false
        },
        "player_id": {
          "name": "player_id",
          "type": "text",
          "primaryKey": false,
          "notNull": true,
          "autoincrement": false
        },
        "scoreable_id": {
          "name": "scoreable_id",
          "type": "text",
          "primaryKey": false,
          "notNull": true,
          "autoincrement": false
        },
        "scoreable_name": {
          "name": "scoreable_name",
          "type": "text",
          "primaryKey": false,
          "notNull": true,
          "autoincrement": false,
          "default": "''"
        },
        "prior_event_id": {
          "name": "prior_event_id",
          "type": "text",
          "primaryKey": false,
          "notNull": false,
          "autoincrement": false
        },
        "note": {
          "name": "note",
          "type": "text",
          "primaryKey": false,
          "notNull": false,
          "autoincrement": false
        },
        "value": {
          "name": "value",
          "type": "real",
          "primaryKey": false,
          "notNull": false,
          "autoincrement": false
        }
      },
      "indexes": {
        "event_player_scoreable_ts": {
          "name": "event_player_scoreable_ts",
          "columns": [
            "player_id",
            "scoreable_id",
            "ts"
          ],
          "isUnique": false
        },
        "event_prior": {
          "name": "event_prior",
          "columns": [
            "prior_event_id"
          ],
          "isUnique": false
        }
      },
      "foreignKeys": {
        "event_player_id_player_id_fk": {
          "name": "event_player_id_player_id_fk",
          "tableFrom": "event",
          "tableTo": "player",
          "columnsFrom": [
            "player_id"
          ],
          "columnsTo": [
            "id"
          ],
          "onDelete": "no action",
          "onUpdate": "no action"
        },
        "event_scoreable_id_scoreable_id_fk": {
          "name": "event_scoreable_id_scoreable_id_fk",
          "tableFrom": "event",
          "tableTo": "scoreable",
          "columnsFrom": [
            "scoreable_id"
          ],
          "columnsTo": [
            "id"
          ],
          "onDelete": "no action",
          "onUpdate": "no action"
        },
        "event_prior_fk": {
          "name": "event_prior_fk",
          "tableFrom": "event",
          "tableTo": "event",
          "columnsFrom": [
            "prior_event_id"
          ],
          "columnsTo": [
            "id"
          ],
          "onDelete": "restrict",
          "onUpdate": "cascade"
        }
      },
      "compositePrimaryKeys": {},
      "uniqueConstraints": {},
      "checkConstraints": {}
    },
    "player": {
      "name": "player",
      "columns": {
        "id": {
          "name": "id",
          "type": "text",
          "primaryKey": true,
          "notNull": true,
          "autoincrement": false
        },
        "first_name": {
          "name": "first_name",
          "type": "text",
          "primaryKey": false,
          "notNull": true,
          "autoincrement": false
        },
        "last_name": {
          "name": "last_name",
          "type": "text",
          "primaryKey": false,
          "notNull": true,
          "autoincrement": false
        },
        "display_name": {
          "name": "display_name",
          "type": "text",
          "primaryKey": false,
          "notNull": true,
          "autoincrement": false
        },
        "email": {
          "name": "email",
          "type": "text",
          "primaryKey": false,
          "notNull": true,
          "autoincrement": false
        },
        "created_at": {
          "name": "created_at",
          "type": "integer",
          "primaryKey": false,
          "notNull": true,
          "autoincrement": false
        },
        "updated_at": {
          "name": "updated_at",
          "type": "integer",
          "primaryKey": false,
          "notNull": true,
          "autoincrement": false
        },
        "emergency_contact": {
          "name": "emergency_contact",
          "type": "text",
          "primaryKey": false,
          "notNull": false,
          "autoincrement": false
        },
        "cell_phone": {
          "name": "cell_phone",
          "type": "text",
          "primaryKey": false,
          "notNull": false,
          "autoincrement": false
        }
      },
      "indexes": {
        "player_email_first_last": {
          "name": "player_email_first_last",
          "columns": [
            "email",
            "first_name",
            "last_name"
          ],
          "isUnique": true
        }
      },
      "foreignKeys": {},
      "compositePrimaryKeys": {},
      "uniqueConstraints": {},
      "checkConstraints": {}
    },
    "player_division": {
      "name": "player_division",
      "columns": {
        "player_id": {
          "name": "player_id",
          "type": "text",
          "primaryKey": false,
          "notNull": true,
          "autoincrement": false
        },
        "division_id": {
          "name": "division_id",
          "type": "text",
          "primaryKey": false,
          "notNull": true,
          "autoincrement": false
        }
      },
      "indexes": {
        "player_division_division": {
          "name": "player_division_division",
          "columns": [
            "division_id"
          ],
          "isUnique": false
        },
        "player_division_player": {
          "name": "player_division_player",
          "columns": [
            "player_id"
          ],
          "isUnique": false
        }
      },
      "foreignKeys": {
        "player_division_player_id_player_id_fk": {
          "name": "player_division_player_id_player_id_fk",
          "tableFrom": "player_division",
          "tableTo": "player",
          "columnsFrom": [
            "player_id"
          ],
          "columnsTo": [
            "id"
          ],
          "onDelete": "cascade",
          "onUpdate": "cascade"
        },
        "player_division_division_id_division_id_fk": {
          "name": "player_division_division_id_division_id_fk",
          "tableFrom": "player_division",
          "tableTo": "division",
          "columnsFrom": [
            "division_id"
          ],
          "columnsTo": [
            "id"
          ],
          "onDelete": "cascade",
          "onUpdate": "cascade"
        }
      },
      "compositePrimaryKeys": {
        "player_division_pk": {
          "columns": [
            "player_id",
            "division_id"
          ],
          "name": "player_division_pk"
        }
      },
      "uniqueConstraints": {},
      "checkConstraints": {}
    },
    "scoreable": {
      "name": "scoreable",
      "columns": {
        "id": {
          "name": "id",
          "type": "text",
          "primaryKey": true,
          "notNull": true,
          "autoincrement": false
        },
        "label": {
          "name": "label",
          "type": "text",
          "primaryKey": false,
          "notNull": true,
          "autoincrement": false
        },
        "unit": {
          "name": "unit",
          "type": "text",
          "primaryKey": false,
          "notNull": true,
          "autoincrement": false
        },
        "created_at": {
          "name": "created_at",
          "type": "integer",
          "primaryKey": false,
          "notNull": true,
          "autoincrement": false
        },
        "updated_at": {
          "name": "updated_at",
          "type": "integer",
          "primaryKey": false,
          "notNull": true,
          "autoincrement": false
        }
      },
      "indexes": {
        "uniq_scoreable_label": {
          "name": "uniq_scoreable_label",
          "columns": [
            "label"
          ],
          "isUnique": true
        }
      },
      "foreignKeys": {},
      "compositePrimaryKeys": {},
      "uniqueConstraints": {},
      "checkConstraints": {}
    }
  },
  "views": {},
  "enums": {},
  "_meta": {
    "schemas": {},
    "tables": {},
    "columns": {}
  },
  "internal": {
    "indexes": {}
  }
}