{
  "version": "7",
  "dialect": "sqlite",
  "entries": [
    {
      "idx": 0,
      "version": "6",
      "when": 1761283897878,
      "tag": "0000_exotic_human_cannonball",
      "breakpoints": true
    },
    {
      "idx": 1,
      "version": "6",
      "when": 1761323090661,
      "tag": "0001_amused_songbird",
      "breakpoints": true
    },
    {
      "idx": 2,
      "version": "6",
      "when": 1761695143123,
      "tag": "0002_shocking_nicolaos",
      "breakpoints": true
    }
  ]
}